albertson
