Metadata-Version: 1.0
Name: Albertson
Version: 0.1.8
Summary: Easy to use, scalable, counters powered by Amazon's DynamoDB
Home-page: https://github.com/FocusLab/Albertson
Author: Sean O'Connor
Author-email: sean@focuslab.io
License: BSD
Platform: UNKNOWN
Classifier: Development Status :: 2 - Pre-Alpha
Classifier: Intended Audience :: Developers
Classifier: License :: OSI Approved :: BSD License
Classifier: Programming Language :: Python
Classifier: Topic :: Software Development :: Libraries :: Python Modules
